findpapers/__init__.py
findpapers/cli.py
findpapers/models/__init__.py
findpapers/models/paper.py
findpapers/models/publication.py
findpapers/models/search.py
findpapers/searchers/__init__.py
findpapers/searchers/acm_searcher.py
findpapers/searchers/arxiv_searcher.py
findpapers/searchers/biorxiv_searcher.py
findpapers/searchers/ieee_searcher.py
findpapers/searchers/medrxiv_searcher.py
findpapers/searchers/pubmed_searcher.py
findpapers/searchers/rxiv_searcher.py
findpapers/searchers/scopus_searcher.py
findpapers/tools/__init__.py
findpapers/tools/bibtex_generator_tool.py
findpapers/tools/downloader_tool.py
findpapers/tools/refiner_tool.py
findpapers/tools/search_runner_tool.py
findpapers/utils/common_util.py
findpapers/utils/persistence_util.py
findpapers/utils/publication_util.py
findpapers/utils/query_util.py
findpapers/utils/requests_util.py
findpapers-0.6.7.dist-info/entry_points.txt
findpapers-0.6.7.dist-info/LICENSE
findpapers-0.6.7.dist-info/WHEEL
findpapers-0.6.7.dist-info/METADATA
findpapers-0.6.7.dist-info/RECORD
