Metadata-Version: 2.1
Name: findpapers
Version: 0.6.7
Summary: Findpapers is an application that helps researchers who are looking for references for their work.
Home-page: https://github.com/jonatasgrosman/findpapers
License: MIT
Keywords: academic,academic publications,academic publishing,acm,arxiv,bibtex,biorxiv,collect papers,crawler,ieee,medrxiv,paper,papers,pubmed,research,scientific papers,scientific publications,scientific publishing,scopus,scraper,systematic mapping,systematic review
Author: Jonatas Grosman
Author-email: jonatasgrosman@gmail.com
Maintainer: Jonatas Grosman
Maintainer-email: jonatasgrosman@gmail.com
Requires-Python: >=3.7,<4.0
Classifier: License :: OSI Approved :: MIT License
Classifier: Programming Language :: Python :: 3
Classifier: Programming Language :: Python :: 3.7
Classifier: Programming Language :: Python :: 3.8
Classifier: Programming Language :: Python :: 3.9
Classifier: Programming Language :: Python :: 3.10
Classifier: Programming Language :: Python :: 3.11
Requires-Dist: colorama (>=0.4.3,<0.5.0)
Requires-Dist: edlib (>=1.3.8,<2.0.0)
Requires-Dist: importlib-metadata (>=1.0,<2.0); python_version < "3.8"
Requires-Dist: inquirer (>=2.7.0,<3.0.0)
Requires-Dist: lxml (>=4.5.2,<5.0.0)
Requires-Dist: requests (>=2.24.0,<3.0.0)
Requires-Dist: typer (>=0.3.2,<0.4.0)
Requires-Dist: xmltodict (>=0.12.0,<0.13.0)
Project-URL: Documentation, https://github.com/jonatasgrosman/findpapers
Project-URL: Repository, https://github.com/jonatasgrosman/findpapers
Project-URL: issues, https://github.com/jonatasgrosman/findpapers/issues
